CHANGES.txt
LICENSE
MANIFEST.in
README.md
pyproject.toml
setup.cfg
setup.py
tox.ini
src/metadata_utils/__init__.py
src/metadata_utils/py.typed
src/metadata_utils.egg-info/PKG-INFO
src/metadata_utils.egg-info/SOURCES.txt
src/metadata_utils.egg-info/dependency_links.txt
src/metadata_utils.egg-info/not-zip-safe
src/metadata_utils.egg-info/requires.txt
src/metadata_utils.egg-info/top_level.txt
tests/__init__.py
tests/test_core.py