Metadata-Version: 2.1
Name: metadata-utils
Version: 0.2.1
Summary: Lightweight Metadata Support
Home-page: https://github.com/jvanasco/metadata_utils
Author: Jonathan Vanasco
Author-email: jonathan@findmeon.com
License: MIT
Keywords: web
Classifier: Intended Audience :: Developers
Classifier: Programming Language :: Python
Classifier: Programming Language :: Python :: 3
Classifier: Programming Language :: Python :: 3.6
Classifier: Programming Language :: Python :: 3.7
Classifier: Programming Language :: Python :: 3.8
Classifier: Programming Language :: Python :: 3.9
Classifier: Programming Language :: Python :: 3.10
Classifier: Programming Language :: Python :: 3.11
Classifier: License :: OSI Approved :: MIT License
Requires-Python: >=3.6
Provides-Extra: testing
License-File: LICENSE
